README.rst
setup.py
coinbase/__init__.py
coinbase/models.py
coinbase/signals.py
coinbase/tests.py
coinbase/urls.py
coinbase/views.py
django_coinbase.egg-info/PKG-INFO
django_coinbase.egg-info/SOURCES.txt
django_coinbase.egg-info/dependency_links.txt
django_coinbase.egg-info/not-zip-safe
django_coinbase.egg-info/requires.txt
django_coinbase.egg-info/top_level.txt