Metadata-Version: 1.1
Name: django-coinbase
Version: 0.2
Summary: a Django app for receiving payment notifications from Coinbase
Home-page: https://github.com/eldarion/django-coinbase
Author: Patrick Altman
Author-email: paltman@eldarion.com
License: BSD
Platform: UNKNOWN
Classifier: Development Status :: 3 - Alpha
Classifier: Environment :: Web Environment
Classifier: Intended Audience :: Developers
Classifier: License :: OSI Approved :: BSD License
Classifier: Operating System :: OS Independent
Classifier: Programming Language :: Python
Classifier: Framework :: Django
